{
    "country": "Afghanistan",
    "data": {
        "Diesel prices": {
            "Date": "11.12.2023",
            "Currency": "71",
            "USD": "1.03"
        },
        "Gasoline prices": {
            "Date": "11.12.2023",
            "Currency": "74",
            "USD": "1.073"
        },
        "Methane prices": {
            "Date": "-",
            "Currency": "-",
            "USD": "-"
        },
        "Ethanol prices": {
            "Date": "-",
            "Currency": "-",
            "USD": "-"
        },
        "Kerosene prices": {
            "Date": "-",
            "Currency": "-",
            "USD": "-"
        },
        "Heating Oil prices": {
            "Date": "-",
            "Currency": "-",
            "USD": "-"
        },
        "LPG prices": {
            "Date": "-",
            "Currency": "-",
            "USD": "-"
        }
    },
    "electricityPrices": {
        "Households": {
            "Date": "01.03.2023",
            "Currency": "3.75",
            "USD": "0.054"
        },
        "Business": {
            "Date": "-",
            "Currency": "-",
            "USD": "-"
        }
    },
    "naturalGasPrices": {
        "Households": {
            "Date": "-",
            "Currency": "-",
            "USD": "-"
        },
        "Business": {
            "Date": "-",
            "Currency": "-",
            "USD": "-"
        }
    }
}