{
    "country": "Cuba",
    "data": {
        "Diesel prices": {
            "Date": "13.11.2023",
            "Currency": "25",
            "USD": "1.05"
        },
        "Gasoline prices": {
            "Date": "13.11.2023",
            "Currency": "30",
            "USD": "1.26"
        },
        "Methane prices": {
            "Date": "-",
            "Currency": "-",
            "USD": "-"
        },
        "Ethanol prices": {
            "Date": "-",
            "Currency": "-",
            "USD": "-"
        },
        "Kerosene prices": {
            "Date": "-",
            "Currency": "-",
            "USD": "-"
        },
        "Heating Oil prices": {
            "Date": "-",
            "Currency": "-",
            "USD": "-"
        },
        "LPG prices": {
            "Date": "-",
            "Currency": "-",
            "USD": "-"
        }
    },
    "electricityPrices": {
        "Households": {
            "Date": "01.03.2023",
            "Currency": "0.72",
            "USD": "0.03"
        },
        "Business": {
            "Date": "-",
            "Currency": "-",
            "USD": "-"
        }
    },
    "naturalGasPrices": {
        "Households": {
            "Date": "-",
            "Currency": "-",
            "USD": "-"
        },
        "Business": {
            "Date": "-",
            "Currency": "-",
            "USD": "-"
        }
    }
}